beeper/__init__.py
beeper/cmd.py
beeper/installer.sh
beeper/utils.py
beeper/builders/__init__.py
beeper/builders/core.py
beeper/builders/python.py
beeper/builders/python_installer.sh
beeper/builders/ruby.py
beeper-0.9.1.dist-info/DESCRIPTION.rst
beeper-0.9.1.dist-info/METADATA
beeper-0.9.1.dist-info/RECORD
beeper-0.9.1.dist-info/WHEEL
beeper-0.9.1.dist-info/entry_points.txt
beeper-0.9.1.dist-info/metadata.json
beeper-0.9.1.dist-info/top_level.txt
tests/__init__.py
tests/beeper.yml
tests/hello.py
tests/requirements.txt
tests/test_cmd.py
