Metadata-Version: 2.0
Name: beeper
Version: 0.9.1
Summary: Bundle virtualenv and project to an artifact.
Home-page: https://github.com/soasme/beeper.py
Author: Ju Lin
Author-email: soasme@gmail.com
License: MIT
Platform: any
Classifier: Intended Audience :: Developers
Classifier: License :: OSI Approved :: MIT License
Classifier: Programming Language :: Python
Classifier: Topic :: Software Development :: Libraries :: Python Modules
Requires-Dist: PyYAML (>=3.11)
Requires-Dist: click (>=6.0)
Requires-Dist: wheel (>=0.10.0)
